{"is_source_file": true, "description": "Simple md file", "external_files": [], "external_methods": [], "published": [], "calls": [], "search-terms": [], "classes": [], "methods": [], "state": 2, "file_id": 29, "knowledge_revision": 67, "git_revision": "caf3344da3b6cd6e4e55552ba6ca3a8d382164d6", "filename": "music_player_frontend/README.md", "hash": "ecaf29ae072beb8364fa679d353950e6", "format-version": 4, "code-base-name": "https://github.com/kavia-common/music-player-pro-4907-4916.git:kavia-main", "revision_history": [{"67": "caf3344da3b6cd6e4e55552ba6ca3a8d382164d6"}]}